{
    "tenants": [
        {
            "id": "tenant-001",
            "name": "Contoso Corp",
            "subscriptions": [
                {
                    "id": "sub-001",
                    "name": "Production",
                    "resourceGroups": [
                        "rg-web",
                        "rg-data",
                        "rg-compute"
                    ],
                    "dates": [
                        "2025-07-01",
                        "2025-08-01",
                        "2025-09-01",
                        "2025-10-01",
                        "2025-11-01",
                        "2025-12-01"
                    ]
                },
                {
                    "id": "sub-002",
                    "name": "Development",
                    "resourceGroups": [
                        "rg-dev-web",
                        "rg-dev-data"
                    ],
                    "dates": [
                        "2025-07-01",
                        "2025-08-01",
                        "2025-09-01",
                        "2025-10-01",
                        "2025-11-01",
                        "2025-12-01"
                    ]
                }
            ]
        }
    ]
}
